application/__init__.py
application/app.py
database/__init__.py
database/firebase.py
pipelinedummy2001-0.0.1.dist-info/LICENSE
pipelinedummy2001-0.0.1.dist-info/METADATA
pipelinedummy2001-0.0.1.dist-info/WHEEL
pipelinedummy2001-0.0.1.dist-info/top_level.txt
pipelinedummy2001-0.0.1.dist-info/RECORD
