Metadata-Version: 2.1
Name: pipelinedummy2001
Version: 0.0.1
Summary: Questo assignment si concentra sulla creazione di un'applicazione che conta e monitora le visualizzazioni degli utenti
Author: ficaradami
Author-email: damianoficara@gmail.com,c.ricci19@campus.unimib.it,emiliotoli21@gmail.com, ficaradami@gmail.com
License: MIT
License-File: LICENSE
